betsee/__init__.py
betsee/__main__.py
betsee/guiappmeta.py
betsee/guiexception.py
betsee/guiignition.py
betsee/guimetaapp.py
betsee/guimetadata.py
betsee/guimetadeps.py
betsee/cli/__init__.py
betsee/cli/guicli.py
betsee/data/py/betsee_rc.py
betsee/data/py/betsee_ui.py
betsee/data/qrc/betsee.qrc
betsee/data/qrc/icon/betsee/advanced.svg
betsee/data/qrc/icon/betsee/chemical.svg
betsee/data/qrc/icon/betsee/dna.svg
betsee/data/qrc/icon/betsee/document_open.svg
betsee/data/qrc/icon/betsee/lineplot.svg
betsee/data/qrc/icon/betsee/planet.svg
betsee/data/qrc/icon/entypo+/clipboard.svg
betsee/data/qrc/icon/entypo+/copy.svg
betsee/data/qrc/icon/entypo+/dot-single.svg
betsee/data/qrc/icon/entypo+/level-down.svg
betsee/data/qrc/icon/entypo+/line-graph.svg
betsee/data/qrc/icon/entypo+/network.svg
betsee/data/qrc/icon/entypo+/scissors.svg
betsee/data/qrc/icon/entypo+/sports-club.svg
betsee/data/qrc/icon/nounproject/maxim_kulikov/cow_flower_square.png
betsee/data/qrc/icon/open_iconic/action-redo.svg
betsee/data/qrc/icon/open_iconic/action-undo.svg
betsee/data/qrc/icon/open_iconic/aperture.svg
betsee/data/qrc/icon/open_iconic/bar-chart.svg
betsee/data/qrc/icon/open_iconic/bars.svg
betsee/data/qrc/icon/open_iconic/bolt.svg
betsee/data/qrc/icon/open_iconic/clipboard.svg
betsee/data/qrc/icon/open_iconic/clock.svg
betsee/data/qrc/icon/open_iconic/document.svg
betsee/data/qrc/icon/open_iconic/external-link.svg
betsee/data/qrc/icon/open_iconic/eyedropper.svg
betsee/data/qrc/icon/open_iconic/file.svg
betsee/data/qrc/icon/open_iconic/folder.svg
betsee/data/qrc/icon/open_iconic/image.svg
betsee/data/qrc/icon/open_iconic/list.svg
betsee/data/qrc/icon/open_iconic/lock-locked.svg
betsee/data/qrc/icon/open_iconic/lock-unlocked.svg
betsee/data/qrc/icon/open_iconic/media-pause.svg
betsee/data/qrc/icon/open_iconic/media-play.svg
betsee/data/qrc/icon/open_iconic/media-stop.svg
betsee/data/qrc/icon/open_iconic/minus.svg
betsee-1.1.1.0.dist-info/DESCRIPTION.rst
betsee-1.1.1.0.dist-info/LICENSE.txt
betsee-1.1.1.0.dist-info/METADATA
betsee-1.1.1.0.dist-info/RECORD
betsee-1.1.1.0.dist-info/WHEEL
betsee-1.1.1.0.dist-info/entry_points.txt
betsee-1.1.1.0.dist-info/metadata.json
betsee-1.1.1.0.dist-info/top_level.txt
