Metadata-Version: 2.0
Name: betsee
Version: 1.1.1.0
Summary: BETSEE, the BioElectric Tissue Simulation Engine Environment.
Home-page: https://gitlab.com/betse/betsee
Author: Alexis Pietak, Cecil Curry, et al.
Author-email: leycec@gmail.com
Maintainer: Alexis Pietak, Cecil Curry, et al.
Maintainer-email: leycec@gmail.com
License: 2-clause BSD
Download-URL: https://gitlab.com/betse/betsee/repository/archive.tar.gz?ref=v1.1.1.0
Keywords: biology,multiphysics,science,simulator
Platform: UNKNOWN
Classifier: Development Status :: 5 - Production/Stable
Classifier: Environment :: MacOS X
Classifier: Environment :: Win32 (MS Windows)
Classifier: Environment :: X11 Applications
Classifier: Intended Audience :: Science/Research
Classifier: License :: OSI Approved :: BSD License
Classifier: Natural Language :: English
Classifier: Operating System :: OS Independent
Classifier: Topic :: Scientific/Engineering :: Bio-Informatics
Requires-Python: >=3.5.0
Provides-Extra: all
Provides-Extra: test
Requires-Dist: PySide2 (>=5.12.3)
Requires-Dist: betse (==1.1.1)
Requires-Dist: setuptools (>=38.2.0)
Provides-Extra: all
Provides-Extra: test
Requires-Dist: pytest (>=3.7.0); extra == 'test'
Requires-Dist: pytest-qt (>=3.2.0); extra == 'test'
Requires-Dist: pytest-xvfb (>=1.2.0); extra == 'test'
Requires-Dist: setuptools (>=38.2.0); extra == 'test'
